makenew_python_package/__init__.py
makenew_python_package-2.0.0.dist-info/LICENSE.txt
makenew_python_package-2.0.0.dist-info/METADATA
makenew_python_package-2.0.0.dist-info/WHEEL
makenew_python_package-2.0.0.dist-info/top_level.txt
makenew_python_package-2.0.0.dist-info/RECORD
