Metadata-Version: 2.1
Name: makenew-python-package
Version: 2.0.0
Summary: Package skeleton for a python module.
Home-page: https://github.com/makenew/python-package
Author: Evan Sosenko
Author-email: razorx@evansosenko.com
License: MIT
Platform: UNKNOWN
